mxx/__init__.py
mxx/cfg_tool/__init__.py
mxx/cfg_tool/__main__.py
mxx/cfg_tool/app.py
mxx/cfg_tool/cfg.py
mxx/cfg_tool/registry.py
mxx/client/__init__.py
mxx/client/client.py
mxx/runner/__init__.py
mxx/runner/builtins/__init__.py
mxx/runner/builtins/app_launcher.py
mxx/runner/builtins/lifetime.py
mxx/runner/builtins/mxxrun.py
mxx/runner/builtins/mxxset.py
mxx/runner/builtins/os_exec.py
mxx/runner/core/__init__.py
mxx/runner/core/callstack.py
mxx/runner/core/config_loader.py
mxx/runner/core/enums.py
mxx/runner/core/plugin.py
mxx/runner/core/registry.py
mxx/runner/core/runner.py
mxx/server/__init__.py
mxx/server/flask_runner.py
mxx/server/registry.py
mxx/server/routes.py
mxx/server/schedule.py
mxx/server/scheduler.py
mxx/server/server.py
mxx/utils/__init__.py
mxx/utils/nested.py
mxx_tool-0.2.0.dist-info/licenses/LICENSE
mxx_tool-0.2.0.dist-info/METADATA
mxx_tool-0.2.0.dist-info/WHEEL
mxx_tool-0.2.0.dist-info/entry_points.txt
mxx_tool-0.2.0.dist-info/top_level.txt
mxx_tool-0.2.0.dist-info/RECORD
