Metadata-Version: 2.4
Name: mxx-tool
Version: 0.2.0
Summary: mxx tool for automating and managing mxx framework/boilerplate projects.
Author-email: ZackaryW <36378555+ZackaryW@users.noreply.github.com>
Requires-Python: >=3.12
License-File: LICENSE
Requires-Dist: pyyaml>=6.0.3
Requires-Dist: tomli>=2.3.0
Requires-Dist: click>=8.1.0
Provides-Extra: server
Requires-Dist: flask>=3.0.0; extra == "server"
Requires-Dist: apscheduler>=3.10.0; extra == "server"
Provides-Extra: client
Requires-Dist: requests>=2.31.0; extra == "client"
Provides-Extra: all
Requires-Dist: mxx-tool[client,server]; extra == "all"
Dynamic: license-file
